{
  "type": "Project",
  "id": "11690",
  "url": "residential/marian-place-bethnal-green",
  "serializeDate": "'2022-06-21 14:17:05.807'",
  "serialized": 1655821025807,
  "serializedBy": "sreeve",
  "title": "Marian Place Bethnal Green",
  "description": ".",
  "date": "2018 -",
  "client": "St William Homes LLP",
  "location": "London, UK",
  "longLat": "-0.061724539814304785  / 51.53424062905374",
  "longitude": "-0.061724539814304785 ",
  "latitude": "51.53424062905374",
  "typologies": [
    "Residential"
  ],
  "team": [
    "Lily Amar",
    "Uday Berry",
    "Alessandro Blasucci",
    "Maurice Brennan",
    "Jean Corona",
    "Luca D'Amico",
    "Kelly Darlington",
    "John Dent",
    "Sandra Goddard",
    "Katherine Hegab",
    "Ed Hiscock",
    "Toby Jeavons",
    "Will Jefferies",
    "Anja Kempa",
    "John Kennedy",
    "Adam Lampon",
    "Stephen Light",
    "Tracy Meller",
    "Nicholas Mitchell",
    "Andrew Morris",
    "Jo Murtagh",
    "Jack Newton",
    "Mark Ng",
    "Joanna Pencakowski",
    "Anna Sebastia",
    "Peter Shannon",
    "Alleen Siu",
    "Graham Stirk",
    "Alejandro Terron",
    "Adeline Wee",
    "Andrew Yek"
  ],
  "partners": [
    "Graham Stirk",
    "Tracy Meller",
    "Andrew Morris",
    "Stephen Light"
  ],
  "leaders": [
    "Graham Stirk"
  ],
  "heights": [
    {
      "label": "Building A",
      "value": "47.485m / 155.79ft",
      "id": "F34E39B7BAC14337BCB76C"
    },
    {
      "label": "Building B",
      "value": "32.625m / 107.021ft",
      "id": "cf52edac07f04cd78add40f1ed887fda"
    },
    {
      "label": "Building C",
      "value": "45.225m / 148.37ft",
      "id": "f0468689ea9d43119243a5d1892fcbcd"
    },
    {
      "label": "Building D",
      "value": "38.925m / 127.70ft",
      "id": "987baa066ba24b65b1f97678fa62c26e"
    },
    {
      "label": "Building E",
      "value": "23.175m / 76.03ft",
      "id": "6b1432a67fc44a428df470b37185fed8"
    }
  ],
  "floors": [
    {
      "value": "6-13",
      "id": "582F6DF09EED4E4AB84F3F"
    }
  ],
  "overview": "Marian Place Bethnal Green will celebrate the unique industrial character of a London gasholder site, providing 555 new private and affordable homes; new spaces for jobs, socialising and leisure, and 1.75 acres of public open space and landscaping - all of which will be framed by Regent’s Canal and identified by the retention of the two existing iconic gasholder frames.\n\nThe scheme comprises 5 faceted buildings ranging from 6 – 13 storeys, which, in addition to the high-quality new homes, will provide 4,182sqm of flexible non-residential floorspace.\n\n\nGasholders no.2 and no.5 will be dismantled, refurbished, and reinstated to create a strong architectural narrative driven by an understanding of the industrial heritage of the site.\n\nResidential apartments will benefit from uninterrupted views of the landscape, the existing gasholder frames, Regent’s Canal, and mid and long-distance views between and beyond neighbouring buildings. Separating accommodation into five buildings will maximise visual and pedestrian permeability through the site.\n\n\nThe scheme will unify the townscape condition and generate new cross-site links to join neighbouring areas. This physical reintegration of the site into the surrounding area will permit the site adjacencies to naturally grow as well as developing Regent’s Canal’s substantial frontage, making it publicly accessible.",
  "dimensions": [
    {
      "label": "Site Area",
      "value": "4.53 acres",
      "id": "e8968dd341144397869ed2a4833b7ff0"
    },
    {
      "label": "Net Residential Area",
      "value": "38,400m2 (net sellable area)<br>",
      "id": "11598f36e0ea4b1e86cac214916bb607"
    }
  ],
  "companies": [
    {
      "label": "Structural Engineer",
      "value": "WSP",
      "id": "b313e2a5afdc4a6186e9bbad56df751d"
    },
    {
      "label": "MEP",
      "value": "WSP",
      "id": "49e22a931eb84ed5afa1b669e0cb1f8f"
    },
    {
      "label": "Planning Consultant",
      "value": "Montagu Evans",
      "id": "fcd9531a87f64d2783f5a6dd6b18cb52"
    },
    {
      "label": "Ecology Consultant",
      "value": "Ecology Solutions",
      "id": "78ff4345d95e43308262a42bba33cb6b"
    },
    {
      "label": "Transport Consultant",
      "value": "TPP",
      "id": "9284985385b84b3a87e026c160f24082"
    },
    {
      "label": "Engineering Consultant",
      "value": "WSP",
      "id": "67d3d7162ab347329467870983f022a4"
    },
    {
      "label": "Right to Light Consultant",
      "value": "Point 2",
      "id": "ab0baf5de16e4e0791fdc2b2a85eddaa"
    },
    {
      "label": "Landscape Architect",
      "value": "Gillespies",
      "id": "7c4a0b72be83412083a150616149f4c4"
    },
    {
      "label": "Architecture and Heritage consultant",
      "value": "Tavernor Consultancy",
      "id": "72754bb7ee9846e2aae69d35c96a9a90"
    }
  ],
  "awards": []
}
